trezor_file_encryption/__init__.py
trezor_file_encryption/command_line.py
trezor_file_encryption/crypt.py
trezor_file_encryption/files.py
trezor_file_encryption/session.py
trezor_file_encryption/trezor.py
trezor_file_encryption-0.0.2.dist-info/LICENSE
trezor_file_encryption-0.0.2.dist-info/METADATA
trezor_file_encryption-0.0.2.dist-info/WHEEL
trezor_file_encryption-0.0.2.dist-info/entry_points.txt
trezor_file_encryption-0.0.2.dist-info/top_level.txt
trezor_file_encryption-0.0.2.dist-info/RECORD
